odoo/addons/l10n_it_fatturapa_out_oss/README.rst
odoo/addons/l10n_it_fatturapa_out_oss/__init__.py
odoo/addons/l10n_it_fatturapa_out_oss/__manifest__.py
odoo/addons/l10n_it_fatturapa_out_oss/data/invoice_it_template.xml
odoo/addons/l10n_it_fatturapa_out_oss/i18n/it.po
odoo/addons/l10n_it_fatturapa_out_oss/i18n/l10n_it_fatturapa_out_oss.pot
odoo/addons/l10n_it_fatturapa_out_oss/readme/CONTRIBUTORS.md
odoo/addons/l10n_it_fatturapa_out_oss/readme/DESCRIPTION.md
odoo/addons/l10n_it_fatturapa_out_oss/static/description/icon.png
odoo/addons/l10n_it_fatturapa_out_oss/static/description/index.html
odoo/addons/l10n_it_fatturapa_out_oss/tests/__init__.py
odoo/addons/l10n_it_fatturapa_out_oss/tests/fatturapa_common.py
odoo/addons/l10n_it_fatturapa_out_oss/tests/test_fatturapa_xml_validation.py
odoo/addons/l10n_it_fatturapa_out_oss/tests/data/IT06363391001_00001.xml
odoo/addons/l10n_it_fatturapa_out_oss/tests/data/IT06363391001_00002.xml
odoo/addons/l10n_it_fatturapa_out_oss/wizard/__init__.py
odoo/addons/l10n_it_fatturapa_out_oss/wizard/l10n_eu_oss_wizard.py
odoo/addons/l10n_it_fatturapa_out_oss/wizard/wizard_export_fatturapa.py
odoo_addon_l10n_it_fatturapa_out_oss-16.0.1.0.2.1.dist-info/METADATA
odoo_addon_l10n_it_fatturapa_out_oss-16.0.1.0.2.1.dist-info/WHEEL
odoo_addon_l10n_it_fatturapa_out_oss-16.0.1.0.2.1.dist-info/top_level.txt
odoo_addon_l10n_it_fatturapa_out_oss-16.0.1.0.2.1.dist-info/RECORD
